aiofetch/__init__.py
aiofetch/crawler.py
aiofetch/downloader.py
aiofetch/logger.py
aiofetch/utils.py
aiofetch-0.0.6.dist-info/LICENSE.md
aiofetch-0.0.6.dist-info/METADATA
aiofetch-0.0.6.dist-info/WHEEL
aiofetch-0.0.6.dist-info/top_level.txt
aiofetch-0.0.6.dist-info/RECORD
