Metadata-Version: 2.2
Name: aiofetch
Version: 0.0.6
Summary: Collection of different tools for async web scraping, crawling and parsing
Author-email: Akram Rakhmetulla <akram042006@gmail.com>
Maintainer-email: Akram Rakhmetulla <akram042006@gmail.com>
License: The MIT License (MIT)
Project-URL: Homepage, https://github.com/spike1236/aiofetch
Project-URL: Issues, https://github.com/spike1236/aiofetch/issues
Classifier: Development Status :: 4 - Beta
Classifier: Framework :: AsyncIO
Classifier: Programming Language :: Python :: 3
Classifier: Programming Language :: Python :: 3.9
Classifier: Programming Language :: Python :: 3.10
Classifier: Programming Language :: Python :: 3.11
Classifier: Programming Language :: Python :: 3.12
Requires-Python: >=3.9
License-File: LICENSE.md
Requires-Dist: aiohttp
Requires-Dist: bs4
Requires-Dist: aiofiles
